chimopy/__init__.py
chimopy/info.py
chimopy/pay.py
chimopy/redeem.py
chimopy/accounts/__init__.py
chimopy/accounts/account.py
chimopy/accounts/wallet.py
chimopy/mobile/__init__.py
chimopy/mobile/transact.py
chimopy-0.0.2.dist-info/LICENSE
chimopy-0.0.2.dist-info/METADATA
chimopy-0.0.2.dist-info/WHEEL
chimopy-0.0.2.dist-info/top_level.txt
chimopy-0.0.2.dist-info/RECORD
