Metadata-Version: 2.1
Name: chimopy
Version: 0.0.2
Summary: A Python wrapper for Chimoney APIs abstracting raw https requests
Home-page: https://github.com/morehwachege/chimopy
Author: Antony Gakuru
Author-email: antony123muriithi@gmail.com
Classifier: Programming Language :: Python
Classifier: License :: OSI Approved :: MIT License
Classifier: Operating System :: OS Independent
License-File: LICENSE
Requires-Dist: requests
